LICENSE.txt
MANIFEST.in
README.md
setup.cfg
setup.py
cdpipelines/__init__.py
cdpipelines/atacseq.py
cdpipelines/convert_bed_to_saf.py
cdpipelines/general.py
cdpipelines/make_mbased_input.py
cdpipelines/make_wasp_input.py
cdpipelines/prepare.py
cdpipelines/rnaseq.py
cdpipelines/scale_bedgraph.py
cdpipelines.egg-info/PKG-INFO
cdpipelines.egg-info/SOURCES.txt
cdpipelines.egg-info/dependency_links.txt
cdpipelines.egg-info/entry_points.txt
cdpipelines.egg-info/top_level.txt
cdpipelines/scripts/mbased.R
cdpipelines/scripts/sortByRef.pl