Metadata-Version: 1.1
Name: cdpipelines
Version: 0.0.7
Summary: Various bioinformatics pipelines.
Home-page: https://github.com/cdeboever3/cdpipelines
Author: Christopher DeBoever
Author-email: cdeboever3@gmail.com
License: MIT
Download-URL: https://github.com/cdeboever3/cdpipelines/tarball/0.0.7
Keywords: bioinformatics
Platform: UNKNOWN
Classifier: Development Status :: 2 - Pre-Alpha
Classifier: Intended Audience :: Science/Research
Classifier: License :: OSI Approved :: MIT License
Classifier: Natural Language :: English
Classifier: Topic :: Scientific/Engineering :: Bio-Informatics
